mcp_network_server/__init__.py
mcp_network_server/server.py
mcp_network_server-0.1.0.dist-info/METADATA
mcp_network_server-0.1.0.dist-info/WHEEL
mcp_network_server-0.1.0.dist-info/entry_points.txt
mcp_network_server-0.1.0.dist-info/RECORD
