Metadata-Version: 2.4
Name: mcp-network-server
Version: 0.1.0
Summary: MCP network server with FastAPI and Socket.IO for machine learning training coordination between multiple devices
Author-email: partymarty2645 <marty.vandenberk@hotmail.com>
Requires-Python: >=3.13
Requires-Dist: mcp>=1.9.2
